data/__init__.py
data/shrynk/__init__.py
data/shrynk/bytes_default.jsonl.gzip
data/shrynk/default.jsonl.gzip
data/shrynk/default_size.pkl
data/shrynk/json_default.jsonl.gzip
data/shrynk/pandas_default.jsonl.gzip
data/shrynk/shrynk_mydata.jsonl
shrynk/__init__.py
shrynk/__main__.py
shrynk/analysis.py
shrynk/bytes.py
shrynk/compressor.py
shrynk/first.py
shrynk/json_.py
shrynk/legacy.py
shrynk/pandas.py
shrynk/pandas_.py
shrynk/predictor.py
shrynk/utils.py
shrynk/classes/__init__.py
shrynk/classes/bytes.py
shrynk/classes/json_.py
shrynk/classes/pandas_.py
shrynk-0.2.25.dist-info/METADATA
shrynk-0.2.25.dist-info/RECORD
shrynk-0.2.25.dist-info/WHEEL
shrynk-0.2.25.dist-info/entry_points.txt
shrynk-0.2.25.dist-info/top_level.txt
