Metadata-Version: 2.1
Name: shrynk
Version: 0.2.25
Summary: Using Machine Learning to learn how to Compress
Home-page: https://github.com/kootenpv/shrynk
Author: Pascal van Kooten
Author-email: kootenpv@gmail.com
License: MIT
Platform: any
Classifier: Intended Audience :: Developers
Classifier: Intended Audience :: Customer Service
Classifier: Intended Audience :: System Administrators
Classifier: Operating System :: Microsoft
Classifier: Operating System :: MacOS :: MacOS X
Classifier: Operating System :: Unix
Classifier: Operating System :: POSIX
Classifier: Programming Language :: Python
Classifier: Programming Language :: Python :: 3
Classifier: Programming Language :: Python :: 3.6
Classifier: Programming Language :: Python :: 3.7
Classifier: Topic :: Software Development
Classifier: Topic :: Software Development :: Libraries
Classifier: Topic :: Software Development :: Libraries :: Python Modules
Classifier: Topic :: System :: Software Distribution
Classifier: Topic :: System :: Systems Administration
Classifier: Topic :: Utilities
Provides-Extra: noc
Provides-Extra: all
Requires-Dist: pandas
Requires-Dist: pyarrow
Requires-Dist: fastparquet
Requires-Dist: sklearn
Requires-Dist: preconvert
Requires-Dist: preconvert-numpy
Requires-Dist: dill
Requires-Dist: wrapt-timeout-decorator
Requires-Dist: just (>=0.7.102)
Requires-Dist: cliche
Provides-Extra: all
Requires-Dist: fastparquet[lz4,brotli,zstandard,snappy,lzo]; extra == 'all'
Provides-Extra: noc
Requires-Dist: fastparquet[snappy,brotli,lz4]; extra == 'noc'
